ba_syx_aas_repository_client/__init__.py
ba_syx_aas_repository_client/api/__init__.py
ba_syx_aas_repository_client/api/asset_administration_shell_repository_api/__init__.py
ba_syx_aas_repository_client/api/asset_administration_shell_repository_api/delete_asset_administration_shell_by_id.py
ba_syx_aas_repository_client/api/asset_administration_shell_repository_api/delete_submodel_reference_by_id_aas_repository.py
ba_syx_aas_repository_client/api/asset_administration_shell_repository_api/delete_thumbnail_aas_repository.py
ba_syx_aas_repository_client/api/asset_administration_shell_repository_api/get_all_asset_administration_shells.py
ba_syx_aas_repository_client/api/asset_administration_shell_repository_api/get_all_submodel_references_aas_repository.py
ba_syx_aas_repository_client/api/asset_administration_shell_repository_api/get_asset_administration_shell_by_id.py
ba_syx_aas_repository_client/api/asset_administration_shell_repository_api/get_asset_information_aas_repository.py
ba_syx_aas_repository_client/api/asset_administration_shell_repository_api/get_thumbnail_aas_repository.py
ba_syx_aas_repository_client/api/asset_administration_shell_repository_api/post_asset_administration_shell.py
ba_syx_aas_repository_client/api/asset_administration_shell_repository_api/post_submodel_reference_aas_repository.py
ba_syx_aas_repository_client/api/asset_administration_shell_repository_api/put_asset_administration_shell_by_id.py
ba_syx_aas_repository_client/api/asset_administration_shell_repository_api/put_asset_information_aas_repository.py
ba_syx_aas_repository_client/api/asset_administration_shell_repository_api/put_thumbnail_aas_repository.py
ba_syx_aas_repository_client/api/registry_and_discovery_interface/__init__.py
ba_syx_aas_repository_client/api/registry_and_discovery_interface/get_description.py
ba_syx_aas_repository_client/client.py
ba_syx_aas_repository_client/errors.py
ba_syx_aas_repository_client/models/__init__.py
ba_syx_aas_repository_client-2.0.dist-info/METADATA
ba_syx_aas_repository_client-2.0.dist-info/WHEEL
ba_syx_aas_repository_client-2.0.dist-info/RECORD
